{"world":[{"date":"2025-10-25","year":"2025","best":39,"time":"0.39","wca_id":"2021YEZI01","name":"Ziyu Ye (叶梓渝)","country":"China","iso":"cn","comp":"HefeiOpen2025"},{"date":"2023-11-04","year":"2023","best":43,"time":"0.43","wca_id":"2021ZAJD03","name":"Teodor Zajder","country":"Poland","iso":"pl","comp":"WarsawCubeMasters2023"},{"date":"2022-11-26","year":"2022","best":47,"time":"0.47","wca_id":"2018WANG35","name":"Guanbo Wang (王冠博)","country":"China","iso":"cn","comp":"NorthsideSpringSaturday2022"},{"date":"2016-03-19","year":"2016","best":49,"time":"0.49","wca_id":"2014CZAP01","name":"Maciej Czapiewski","country":"Poland","iso":"pl","comp":"GrudziadzOpen2016"},{"date":"2015-06-06","year":"2015","best":58,"time":"0.58","wca_id":"2011SBAH01","name":"Rami Sbahi","country":"USA","iso":"us","comp":"CanadianOpen2015"},{"date":"2011-11-12","year":"2011","best":69,"time":"0.69","wca_id":"2009KASE02","name":"Christian Kaserer","country":"Italy","iso":"it","comp":"TrentinOpen2011"},{"date":"2008-11-08","year":"2008","best":96,"time":"0.96","wca_id":"2005AKKE01","name":"Erik Akkersdijk","country":"Netherlands","iso":"nl","comp":"GenevaOpen2008"},{"date":"2008-02-23","year":"2008","best":163,"time":"1.63","wca_id":"2005PARI01","name":"Javier París","country":"Spain","iso":"es","comp":"MurciaOpen2008"},{"date":"2007-11-10","year":"2007","best":265,"time":"2.65","wca_id":"2003BRUC01","name":"Ron van Bruchem","country":"Netherlands","iso":"nl","comp":"UKOpen2007"},{"date":"2007-07-14","year":"2007","best":273,"time":"2.73","wca_id":"2006KUTI01","name":"Mátyás Kuti","country":"Hungary","iso":"hu","comp":"CzechOpen2007"},{"date":"2006-05-27","year":"2006","best":355,"time":"3.55","wca_id":"2005HSUA01","name":"Anthony Hsu","country":"USA","iso":"us","comp":"Trumbull2006"},{"date":"2005-12-11","year":"2005","best":394,"time":"3.94","wca_id":"2004KRIG01","name":"Gunnar Krig","country":"Sweden","iso":"se","comp":"SwedishCubeday2005"},{"date":"2005-05-28","year":"2005","best":413,"time":"4.13","wca_id":"2003MAKI01","name":"Shotaro Makisumi (牧角章太郎)","country":"Japan","iso":"jp","comp":"HoraceMann2005"},{"date":"2005-04-16","year":"2005","best":492,"time":"4.92","wca_id":"2003MAKI01","name":"Shotaro Makisumi (牧角章太郎)","country":"Japan","iso":"jp","comp":"CaltechSpring2005"},{"date":"2005-03-27","year":"2005","best":635,"time":"6.35","wca_id":"2004KRIG01","name":"Gunnar Krig","country":"Sweden","iso":"se","comp":"Svekub2005"},{"date":"2004-11-27","year":"2004","best":844,"time":"8.44","wca_id":"2004HELL01","name":"Micael Hellberg","country":"Sweden","iso":"se","comp":"Sweden2004"}],"france":[{"date":"2024-05-18","year":"2024","best":78,"time":"0.78","wca_id":"2014SEBA01","name":"Juliette Sébastien","country":"France","iso":"fr","comp":"BarbyCube2024"},{"date":"2022-07-22","year":"2022","best":80,"time":"0.80","wca_id":"2017CHAM02","name":"Anael Champion","country":"France","iso":"fr","comp":"NorwegianChampionship2022"},{"date":"2017-11-25","year":"2017","best":83,"time":"0.83","wca_id":"2014BEGU01","name":"Elian Beguec","country":"France","iso":"fr","comp":"NancyOpen2017"},{"date":"2016-04-30","year":"2016","best":92,"time":"0.92","wca_id":"2012CARL03","name":"Alexandre Carlier","country":"France","iso":"fr","comp":"France2016"},{"date":"2013-12-21","year":"2013","best":106,"time":"1.06","wca_id":"2012CARL03","name":"Alexandre Carlier","country":"France","iso":"fr","comp":"LaMontagneOpen2013"},{"date":"2010-12-04","year":"2010","best":127,"time":"1.27","wca_id":"2010OLIV01","name":"Auguste Olivry","country":"France","iso":"fr","comp":"LyonSinterklaasOpen2010"},{"date":"2008-11-08","year":"2008","best":139,"time":"1.39","wca_id":"2004CHAM01","name":"Edouard Chambon","country":"France","iso":"fr","comp":"GenevaOpen2008"},{"date":"2008-07-05","year":"2008","best":166,"time":"1.66","wca_id":"2004CHAM01","name":"Edouard Chambon","country":"France","iso":"fr","comp":"ToulouseSummerOpen2008"},{"date":"2008-04-05","year":"2008","best":261,"time":"2.61","wca_id":"2004CHAM01","name":"Edouard Chambon","country":"France","iso":"fr","comp":"MadridOpen2008"},{"date":"2007-11-10","year":"2007","best":283,"time":"2.83","wca_id":"2004GALL02","name":"Clément Gallet","country":"France","iso":"fr","comp":"UKOpen2007"},{"date":"2007-10-05","year":"2007","best":350,"time":"3.50","wca_id":"2006JACQ01","name":"Thibaut Jacquinot","country":"France","iso":"fr","comp":"WC2007"},{"date":"2007-02-04","year":"2007","best":432,"time":"4.32","wca_id":"2006JACQ01","name":"Thibaut Jacquinot","country":"France","iso":"fr","comp":"Roissy2007"},{"date":"2006-09-23","year":"2006","best":619,"time":"6.19","wca_id":"2006JACQ01","name":"Thibaut Jacquinot","country":"France","iso":"fr","comp":"Euro2006"}]}